totalhelp/__about__.py
totalhelp/__init__.py
totalhelp/__main__.py
totalhelp/basic_types.py
totalhelp/external.py
totalhelp/library.py
totalhelp/parser.py
totalhelp/py.typed
totalhelp/ui.py
totalhelp-0.1.0.dist-info/METADATA
totalhelp-0.1.0.dist-info/WHEEL
totalhelp-0.1.0.dist-info/entry_points.txt
totalhelp-0.1.0.dist-info/licenses/LICENSE
totalhelp-0.1.0.dist-info/RECORD
