Metadata-Version: 2.4
Name: totalhelp
Version: 0.1.0
Summary: Print help for all commands and subcommands for argparse applications
Project-URL: Homepage, https://github.com/matthewdeanmartin/totalhelp
Project-URL: Bug Tracker, https://github.com/matthewdeanmartin/totalhelp/issues
Author-email: Matthew Dean Martin <matthewdeanmartin@gmail.com>
License-File: LICENSE
Classifier: Development Status :: 1 - Planning
Classifier: License :: OSI Approved :: MIT License
Classifier: Operating System :: OS Independent
Classifier: Programming Language :: Python
Classifier: Programming Language :: Python :: 3
Classifier: Programming Language :: Python :: 3.8
Classifier: Programming Language :: Python :: 3.9
Classifier: Programming Language :: Python :: 3.10
Classifier: Programming Language :: Python :: 3.11
Classifier: Programming Language :: Python :: 3.12
Classifier: Programming Language :: Python :: 3.13
Classifier: Programming Language :: Python :: 3.14
Classifier: Programming Language :: Python :: 3.15
Classifier: Topic :: Software Development :: Libraries :: Python Modules
Classifier: Topic :: Terminals
Requires-Python: >=3.8
Provides-Extra: rich
Requires-Dist: rich-argparse>=1.0.0; extra == 'rich'
Requires-Dist: rich>=10.0.0; extra == 'rich'
